_fastcsv.c
_fastcsv_reader.c
_fastcsv_writer.c
fastcsv.py
setup.cfg
setup.py
fastcsv.egg-info/PKG-INFO
fastcsv.egg-info/SOURCES.txt
fastcsv.egg-info/dependency_links.txt
fastcsv.egg-info/top_level.txt