Metadata-Version: 1.1
Name: fastcsv
Version: 0.1.0
Summary: fastcsv
Home-page: UNKNOWN
Author: Masaya SUZUKI
Author-email: draftcode@gmail.com
License: UNKNOWN
Platform: UNKNOWN
Classifier: Development Status :: 3 - Alpha
Classifier: License :: OSI Approved :: BSD License
Classifier: Topic :: Text Processing
